weather_applet-1.1.0.data/data/share/applications/weather-applet.desktop
weather_applet-1.1.0.data/scripts/weather-applet
weatherapplet/__init__.py
weatherapplet/owm.py
weatherapplet/prefs.py
weatherapplet/utils.py
weatherapplet/weather.py
weatherapplet/weather_splash.py
weather_applet-1.1.0.dist-info/LICENSE
weather_applet-1.1.0.dist-info/METADATA
weather_applet-1.1.0.dist-info/WHEEL
weather_applet-1.1.0.dist-info/top_level.txt
weather_applet-1.1.0.dist-info/RECORD
