Metadata-Version: 2.1
Name: weather-applet
Version: 1.1.0
Summary: Weather system tray applet using OpenWeatherMap
Home-page: https://github.com/jmechnich/weather-applet
Author: Joerg Mechnich
Author-email: joerg.mechnich@gmail.com
License: GNU GPLv3
Classifier: Programming Language :: Python :: 3
Classifier: License :: OSI Approved :: GNU General Public License v3 (GPLv3)
Classifier: Operating System :: POSIX :: Linux
Classifier: Environment :: X11 Applications :: Qt
Requires-Python: >=3.6
License-File: LICENSE
Requires-Dist: appletlib >=1.1
